mailem/__init__.py
mailem/attachment.py
mailem/message.py
mailem/postman.py
mailem/util.py
mailem/connection/__init__.py
mailem/connection/base.py
mailem/connection/lo.py
mailem/connection/smtp.py
mailem/template/__init__.py
mailem/template/registry.py
mailem/template/renderer.py
mailem/template/template.py
tests/__init__.py
tests/asyncio_utils.py
tests/lo-test.py
tests/message-test.py
tests/smtp-test.py
tests/template-test.py
mailem-0.0.5.dist-info/LICENSE
mailem-0.0.5.dist-info/METADATA
mailem-0.0.5.dist-info/WHEEL
mailem-0.0.5.dist-info/top_level.txt
mailem-0.0.5.dist-info/RECORD
