Metadata-Version: 2.1
Name: mailem
Version: 0.0.5
Summary: Slim, flexible, yet full-featured e-mailing library 
Home-page: https://github.com/kolypto/py-mailem
Author: Mark Vartanyan
Author-email: kolypto@gmail.com
License: BSD
Keywords: e-mail,mail,template
Platform: any
Classifier: Development Status :: 5 - Production/Stable
Classifier: Intended Audience :: Developers
Classifier: Natural Language :: English
Classifier: Operating System :: OS Independent
Classifier: Programming Language :: Python :: 2
Classifier: Programming Language :: Python :: 3
Classifier: Topic :: Software Development :: Libraries :: Python Modules
Requires-Dist: future
